theboss/__init__.py
theboss/boson_sampling_simulator.py
theboss/quantum_computations_utilities.py
theboss/boson_sampling_utilities/__init__.py
theboss/boson_sampling_utilities/boson_sampling_utilities.py
theboss/boson_sampling_utilities/permanent_calculators/__init__.py
theboss/boson_sampling_utilities/permanent_calculators/bs_cc_ch_submatrices_permanent_calculator.py
theboss/boson_sampling_utilities/permanent_calculators/bs_cc_ryser_submatrices_permanent_calculator.py
theboss/boson_sampling_utilities/permanent_calculators/bs_permanent_calculator_base.py
theboss/boson_sampling_utilities/permanent_calculators/bs_permanent_calculator_factory.py
theboss/boson_sampling_utilities/permanent_calculators/bs_permanent_calculator_interface.py
theboss/boson_sampling_utilities/permanent_calculators/bs_submatrices_permanent_calculator_base.py
theboss/boson_sampling_utilities/permanent_calculators/bs_submatrices_permanent_calculator_interface.py
theboss/boson_sampling_utilities/permanent_calculators/chin_huh_permanent_calculator.py
theboss/boson_sampling_utilities/permanent_calculators/classic_permanent_calculator.py
theboss/boson_sampling_utilities/permanent_calculators/glynn_gray_permanent_calculator.py
theboss/boson_sampling_utilities/permanent_calculators/ryser_permanent_calculator.py
theboss/distribution_calculators/__init__.py
theboss/distribution_calculators/bs_appriximated_distribution_from_separable_states_calculator.py
theboss/distribution_calculators/bs_distribution_calculator_interface.py
theboss/distribution_calculators/bs_distribution_calculator_with_fixed_losses.py
theboss/distribution_calculators/bs_exact_distribution_with_uniform_losses.py
theboss/distribution_calculators/bs_sample_based_distribution_calculator.py
theboss/network_simulation_strategy/__init__.py
theboss/network_simulation_strategy/lossless_network_simulation_strategy.py
theboss/network_simulation_strategy/lossy_network_simulation_strategy.py
theboss-3.0.1.dist-info/LICENSE.md
theboss-3.0.1.dist-info/METADATA
theboss-3.0.1.dist-info/WHEEL
theboss-3.0.1.dist-info/top_level.txt
theboss-3.0.1.dist-info/RECORD
