Metadata-Version: 2.1
Name: theboss
Version: 3.0.1
Summary: A package for (Bo)son (S)ampling (S)imulations!
Author: Tomasz Rybotycki
Author-email: rybotycki.tomasz+theboss@gmail.com
License: Apache License 2.0.
Classifier: Intended Audience :: Developers
Classifier: License :: OSI Approved :: Apache Software License
Classifier: Natural Language :: English
License-File: LICENSE.md
Requires-Dist: requests
Requires-Dist: importlib-metadata ; python_version == "3.7"
Requires-Dist: numpy (>=1.19.5) ; python_version >= "3.7"
Requires-Dist: scipy (>=1.5.4) ; python_version >= "3.7"
Requires-Dist: guancodes (>=0.0.3) ; python_version >= "3.7"
